earth_rover_mini_sdk/__init__.py
earth_rover_mini_sdk/api.py
earth_rover_mini_sdk/uart_cp.py
earth_rover_mini_sdk-1.0.1.dist-info/METADATA
earth_rover_mini_sdk-1.0.1.dist-info/WHEEL
earth_rover_mini_sdk-1.0.1.dist-info/licenses/LICENSE
earth_rover_mini_sdk-1.0.1.dist-info/RECORD
