Metadata-Version: 2.4
Name: earth_rover_mini_sdk
Version: 1.0.1
Summary: API for EarthRover Mini. Allows interfacing and control over device through a simple interface.
Project-URL: Homepage, https://github.com/SIGRobotics-UIUC/earth_rover_mini_sdk
Project-URL: Issues, https://github.com/SIGRobotics-UIUC/earth_rover_mini_sdk/issues
Author-email: Saketh Kantipudi <saketh3@illinois.edu>, Hasan Al Saeedi <halsae2@illinois.edu>, Aarsh Mittal <aarshm2@illinois.edu>, Somrishi Banerjee <sb91@illinois.edu>, Sairaj Shetye <sshetye2@illinois.edu>
License-Expression: MIT
License-File: LICENSE
Classifier: Operating System :: OS Independent
Classifier: Programming Language :: Python :: 3
Requires-Python: >=3.9
